LICENSE
README.md
setup.cfg
setup.py
src/destables/__init__.py
src/destables/c11tools.py
src/destables/commonwin.py
src/destables/funcwin.py
src/destables/macroconstwin.py
src/destables/macrofuncwin.py
src/destables/main.py
src/destables/tabhelper.py
src/destables/todo.txt
src/destables/typewin.py
src/destables/varwin.py
src/destables.egg-info/PKG-INFO
src/destables.egg-info/SOURCES.txt
src/destables.egg-info/dependency_links.txt
src/destables.egg-info/entry_points.txt
src/destables.egg-info/requires.txt
src/destables.egg-info/top_level.txt
src/destables/cparser/C11.interp
src/destables/cparser/C11.tokens
src/destables/cparser/C11Lexer.interp
src/destables/cparser/C11Lexer.py
src/destables/cparser/C11Lexer.tokens
src/destables/cparser/C11Parser.py
src/destables/cparser/C11Visitor.py
src/destables/cparser/CLexer.interp
src/destables/cparser/CLexer.py
src/destables/cparser/CLexer.tokens
src/destables/cparser/__init__.py